chainmerger/__init__.py
chainmerger/__main__.py
chainmerger/__version__.py
chainmerger-1.1.1.dist-info/LICENSE
chainmerger-1.1.1.dist-info/METADATA
chainmerger-1.1.1.dist-info/WHEEL
chainmerger-1.1.1.dist-info/entry_points.txt
chainmerger-1.1.1.dist-info/top_level.txt
chainmerger-1.1.1.dist-info/RECORD
