Metadata-Version: 2.1
Name: chainmerger
Version: 1.1.1
Summary: Merge chainalysis csv files into one report file.
Home-page: https://github.com/bitdruid/chainmerger
Author: bitdruid
Author-email: bitdruid@outlook.com
License: MIT
License-File: LICENSE
Requires-Dist: openpyxl ==3.1.2
Requires-Dist: pandas ==2.1.3
Requires-Dist: tldextract ==5.1.0
Requires-Dist: XlsxWriter ==3.1.9
